as_async/__init__.py
as_async-1.0.1.dist-info/LICENSE
as_async-1.0.1.dist-info/METADATA
as_async-1.0.1.dist-info/WHEEL
as_async-1.0.1.dist-info/top_level.txt
as_async-1.0.1.dist-info/RECORD
