Metadata-Version: 2.1
Name: as-async
Version: 1.0.1
Summary: A simple library for unblocking asynchronous code
Author-email: Mathias Örtenberg Toftås <mathias.ortenberg-toftas@outlook.com>
Project-URL: Homepage, https://github.com/MathiasToftas/as-async
Project-URL: Issues, https://github.com/MathiasToftas/as-async/issues
Classifier: Programming Language :: Python :: 3
Classifier: License :: OSI Approved :: MIT License
Classifier: Operating System :: OS Independent
Requires-Python: >=3.12.0
License-File: LICENSE
Provides-Extra: dev
Requires-Dist: pytest ; extra == 'dev'
Requires-Dist: pytest-asyncio ; extra == 'dev'
Requires-Dist: pre-commit ; extra == 'dev'
Requires-Dist: build ; extra == 'dev'
Requires-Dist: twine ; extra == 'dev'
